docs/conf.py
pyrocs/VERSION
pyrocs/__init__.py
pyrocs/version.py
pyrocs/biosciences/__init__.py
pyrocs/biosciences/affinity.py
pyrocs/biosciences/functional_redundancy.py
pyrocs/biosciences/hill_diversity.py
pyrocs/complex_systems/__init__.py
pyrocs/complex_systems/causal_complexity.py
pyrocs/complex_systems/fluctuation_complexity.py
pyrocs/complex_systems/grc.py
pyrocs/information_theory/__init__.py
pyrocs/information_theory/entropy.py
pyrocs/information_theory/kl_divergence.py
pyrocs/information_theory/mutual_info.py
test/test_biosciences.py
test/test_complex_systems.py
test/test_information_theory.py
pyrocs-0.1.1.dist-info/LICENSE.txt
pyrocs-0.1.1.dist-info/METADATA
pyrocs-0.1.1.dist-info/WHEEL
pyrocs-0.1.1.dist-info/top_level.txt
pyrocs-0.1.1.dist-info/RECORD
